holochain_serialization-0.1.0.dist-info/METADATA
holochain_serialization-0.1.0.dist-info/WHEEL
holochain_serialization/__init__.py
holochain_serialization/holochain_serialization.pypy38-pp73-aarch64-linux-gnu.so
holochain_serialization-0.1.0.dist-info/RECORD
